{"attempt_number":2,"action_url":"https://github.com/loginkarun/bank/actions/runs/22752216472","build_workflow_status":"success","build_workflow_output":{"status":"success","attempts":1,"api_url":"https://int-ai.aava.ai/workflows/workflow-executions/a5b08155-6578-4cc2-9bfe-e1415ded3c66","repo":"bank","branch":"main","source_folder":"code","last_error":"","non_retryable":false,"history":[{"attempt":1,"fix_workflow_execution_id":"a5b08155-6578-4cc2-9bfe-e1415ded3c66","status":"triggered"}]},"repo":"bank","branch":"main"}